{
    "output": {
        "blocklist": [],
        "equalizer#0": {
            "balance": 0.0,
            "bypass": false,
            "input-gain": -10.0,
            "left": {
                "band0": {
                    "frequency": 320.0,
                    "gain": -2.4,
                    "mode": "RLC (BT)",
                    "mute": false,
                    "q": 1.0,
                    "slope": "x1",
                    "solo": false,
                    "type": "Bell"
                },
                "band1": {
                    "frequency": 980.0,
                    "gain": -5.8,
                    "mode": "RLC (BT)",
                    "mute": false,
                    "q": 1.5999999999999996,
                    "slope": "x1",
                    "solo": false,
                    "type": "Bell"
                },
                "band10": {
                    "frequency": 110.0,
                    "gain": 2.6,
                    "mode": "RLC (BT)",
                    "mute": false,
                    "q": 1.0,
                    "slope": "x1",
                    "solo": false,
                    "type": "Lo-shelf"
                },
                "band11": {
                    "frequency": 3000.0,
                    "gain": 0.0,
                    "mode": "RLC (BT)",
                    "mute": false,
                    "q": 4.0,
                    "slope": "x1",
                    "solo": false,
                    "type": "Off"
                },
                "band2": {
                    "frequency": 220.0,
                    "gain": -2.6,
                    "mode": "RLC (BT)",
                    "mute": false,
                    "q": 1.0,
                    "slope": "x1",
                    "solo": false,
                    "type": "Lo-shelf"
                },
                "band3": {
                    "frequency": 1600.0,
                    "gain": 4.8,
                    "mode": "RLC (BT)",
                    "mute": false,
                    "q": 1.0,
                    "slope": "x1",
                    "solo": false,
                    "type": "Hi-shelf"
                },
                "band4": {
                    "frequency": 3000.0,
                    "gain": 2.6,
                    "mode": "RLC (BT)",
                    "mute": false,
                    "q": 1.0000000000000002,
                    "slope": "x1",
                    "solo": false,
                    "type": "Bell"
                },
                "band5": {
                    "frequency": 5200.0,
                    "gain": -0.8,
                    "mode": "RLC (BT)",
                    "mute": false,
                    "q": 2.0,
                    "slope": "x1",
                    "solo": false,
                    "type": "Hi-shelf"
                },
                "band6": {
                    "frequency": 640.0,
                    "gain": 0.8,
                    "mode": "RLC (BT)",
                    "mute": false,
                    "q": 0.7999999999999989,
                    "slope": "x1",
                    "solo": false,
                    "type": "Bell"
                },
                "band7": {
                    "frequency": 4200.0,
                    "gain": 3.2,
                    "mode": "RLC (BT)",
                    "mute": false,
                    "q": 1.0,
                    "slope": "x1",
                    "solo": false,
                    "type": "Bell"
                },
                "band8": {
                    "frequency": 9600.0,
                    "gain": -1.3,
                    "mode": "APO (DR)",
                    "mute": false,
                    "q": 2.0,
                    "slope": "x1",
                    "solo": false,
                    "type": "Bell"
                },
                "band9": {
                    "frequency": 140.0,
                    "gain": -1.6,
                    "mode": "APO (DR)",
                    "mute": false,
                    "q": 0.6999999999999997,
                    "slope": "x1",
                    "solo": false,
                    "type": "Lo-shelf"
                }
            },
            "mode": "IIR",
            "num-bands": 12,
            "output-gain": 0.0,
            "pitch-left": 0.0,
            "pitch-right": 0.0,
            "right": {
                "band0": {
                    "frequency": 320.0,
                    "gain": -2.4,
                    "mode": "RLC (BT)",
                    "mute": false,
                    "q": 1.0,
                    "slope": "x1",
                    "solo": false,
                    "type": "Bell"
                },
                "band1": {
                    "frequency": 980.0,
                    "gain": -5.8,
                    "mode": "RLC (BT)",
                    "mute": false,
                    "q": 1.5999999999999996,
                    "slope": "x1",
                    "solo": false,
                    "type": "Bell"
                },
                "band10": {
                    "frequency": 110.0,
                    "gain": 2.6,
                    "mode": "RLC (BT)",
                    "mute": false,
                    "q": 1.0,
                    "slope": "x1",
                    "solo": false,
                    "type": "Lo-shelf"
                },
                "band11": {
                    "frequency": 3000.0,
                    "gain": 0.0,
                    "mode": "RLC (BT)",
                    "mute": false,
                    "q": 4.0,
                    "slope": "x1",
                    "solo": false,
                    "type": "Off"
                },
                "band2": {
                    "frequency": 220.0,
                    "gain": -2.6,
                    "mode": "RLC (BT)",
                    "mute": false,
                    "q": 1.0,
                    "slope": "x1",
                    "solo": false,
                    "type": "Lo-shelf"
                },
                "band3": {
                    "frequency": 1600.0,
                    "gain": 4.8,
                    "mode": "RLC (BT)",
                    "mute": false,
                    "q": 1.0,
                    "slope": "x1",
                    "solo": false,
                    "type": "Hi-shelf"
                },
                "band4": {
                    "frequency": 3000.0,
                    "gain": 2.6,
                    "mode": "RLC (BT)",
                    "mute": false,
                    "q": 1.0000000000000002,
                    "slope": "x1",
                    "solo": false,
                    "type": "Bell"
                },
                "band5": {
                    "frequency": 5200.0,
                    "gain": -0.8,
                    "mode": "RLC (BT)",
                    "mute": false,
                    "q": 2.0,
                    "slope": "x1",
                    "solo": false,
                    "type": "Hi-shelf"
                },
                "band6": {
                    "frequency": 640.0,
                    "gain": 0.8,
                    "mode": "RLC (BT)",
                    "mute": false,
                    "q": 0.7999999999999989,
                    "slope": "x1",
                    "solo": false,
                    "type": "Bell"
                },
                "band7": {
                    "frequency": 4200.0,
                    "gain": 3.2,
                    "mode": "RLC (BT)",
                    "mute": false,
                    "q": 1.0,
                    "slope": "x1",
                    "solo": false,
                    "type": "Bell"
                },
                "band8": {
                    "frequency": 9600.0,
                    "gain": -1.3,
                    "mode": "APO (DR)",
                    "mute": false,
                    "q": 2.0,
                    "slope": "x1",
                    "solo": false,
                    "type": "Bell"
                },
                "band9": {
                    "frequency": 140.0,
                    "gain": -1.6,
                    "mode": "APO (DR)",
                    "mute": false,
                    "q": 0.6999999999999997,
                    "slope": "x1",
                    "solo": false,
                    "type": "Lo-shelf"
                }
            },
            "split-channels": false
        },
        "limiter#0": {
            "alr": false,
            "alr-attack": 5.0,
            "alr-knee": 0.0,
            "alr-release": 50.0,
            "attack": 2.0,
            "bypass": false,
            "dithering": "None",
            "external-sidechain": false,
            "gain-boost": false,
            "input-gain": 0.0,
            "lookahead": 2.0,
            "mode": "Herm Thin",
            "output-gain": 0.0,
            "oversampling": "Full x2(2L)",
            "release": 5.0,
            "sidechain-preamp": 0.0,
            "stereo-link": 100.0,
            "threshold": -0.7999999999999997
        },
        "plugins_order": [
            "equalizer#0",
            "limiter#0"
        ]
    }
}
